twikitminifix-2.3.7.dist-info/METADATA
twikitminifix-2.3.7.dist-info/WHEEL
twikitminifix-2.3.7.dist-info/entry_points.txt
twikitminifix-2.3.7.dist-info/licenses/LICENSE
twikitminifix/__init__.py
twikitminifix/_captcha/__init__.py
twikitminifix/_captcha/base.py
twikitminifix/_captcha/capsolver.py
twikitminifix/bookmark.py
twikitminifix/client/client.py
twikitminifix/client/gql.py
twikitminifix/client/v11.py
twikitminifix/community.py
twikitminifix/constants.py
twikitminifix/errors.py
twikitminifix/geo.py
twikitminifix/group.py
twikitminifix/guest/__init__.py
twikitminifix/guest/client.py
twikitminifix/guest/tweet.py
twikitminifix/guest/user.py
twikitminifix/list.py
twikitminifix/media.py
twikitminifix/message.py
twikitminifix/notification.py
twikitminifix/streaming.py
twikitminifix/trend.py
twikitminifix/tweet.py
twikitminifix/ui_metrics/__init__.py
twikitminifix/ui_metrics/dom.py
twikitminifix/user.py
twikitminifix/utils.py
twikitminifix/x_client_transaction/__init__.py
twikitminifix/x_client_transaction/cubic_curve.py
twikitminifix/x_client_transaction/interpolate.py
twikitminifix/x_client_transaction/rotation.py
twikitminifix/x_client_transaction/transaction.py
twikitminifix/x_client_transaction/utils.py
twikitminifix-2.3.7.dist-info/RECORD
