Metadata-Version: 2.1
Name: twikitminifix
Version: 2.3.7
Summary: Twitter API wrapper for python with **no API key required**.
Author-Email: shapranov.work@gmail.com
License: MIT
Requires-Python: >=3.8
Requires-Dist: httpx[socks]
Requires-Dist: filetype
Requires-Dist: beautifulsoup4
Requires-Dist: pyotp
Requires-Dist: lxml
Requires-Dist: webvtt-py
Requires-Dist: m3u8
Requires-Dist: Js2Py-3-13
